panndas/__init__.py
panndas/data/__init__.py
panndas/data/text.py
panndas/data/utils.py
panndas/nn/__init__.py
panndas/nn/functional.py
panndas/nn/modules/__init__.py
panndas/nn/modules/activation.py
panndas/nn/modules/batchnorm.py
panndas/nn/modules/container.py
panndas/nn/modules/dropout.py
panndas/nn/modules/linear.py
panndas/nn/modules/module.py
panndas/nn/modules/transformer.py
panndas-0.0.2.dist-info/WHEEL
panndas-0.0.2.dist-info/METADATA
panndas-0.0.2.dist-info/RECORD
