Metadata-Version: 2.1
Name: panndas
Version: 0.0.2
Summary: Neural networks in pandas
Home-page: https://github.com/charlesfrye/panndas
License: YOLO
Keywords: pandas,neural networks,jokes
Author: Charles Frye
Author-email: cfrye59@gmail.com
Requires-Python: >=3.7.1,<4.0.0
Classifier: License :: Other/Proprietary License
Classifier: Programming Language :: Python :: 3
Classifier: Programming Language :: Python :: 3.10
Classifier: Programming Language :: Python :: 3.8
Classifier: Programming Language :: Python :: 3.9
Requires-Dist: pandas (>=1.3,<2.0)
Project-URL: Documentation, https://panndas.readthedocs.io
Project-URL: Repository, https://github.com/charlesfrye/panndas
